LICENSE
MANIFEST.in
README.md
setup.cfg
setup.py
django_admin_json_editor/__init__.py
django_admin_json_editor/admin.py
django_admin_json_editor/version.py
django_admin_json_editor.egg-info/PKG-INFO
django_admin_json_editor.egg-info/SOURCES.txt
django_admin_json_editor.egg-info/dependency_links.txt
django_admin_json_editor.egg-info/requires.txt
django_admin_json_editor.egg-info/top_level.txt
django_admin_json_editor/static/django_admin_json_editor/style.css
django_admin_json_editor/static/django_admin_json_editor/bootstrap/css/bootstrap.min.css
django_admin_json_editor/static/django_admin_json_editor/bootstrap/fonts/glyphicons-halflings-regular.eot
django_admin_json_editor/static/django_admin_json_editor/bootstrap/fonts/glyphicons-halflings-regular.svg
django_admin_json_editor/static/django_admin_json_editor/bootstrap/fonts/glyphicons-halflings-regular.ttf
django_admin_json_editor/static/django_admin_json_editor/bootstrap/fonts/glyphicons-halflings-regular.woff
django_admin_json_editor/static/django_admin_json_editor/bootstrap/fonts/glyphicons-halflings-regular.woff2
django_admin_json_editor/static/django_admin_json_editor/bootstrap/js/bootstrap.min.js
django_admin_json_editor/static/django_admin_json_editor/fontawesome/css/font-awesome.min.css
django_admin_json_editor/static/django_admin_json_editor/fontawesome/fonts/FontAwesome.otf
django_admin_json_editor/static/django_admin_json_editor/fontawesome/fonts/fontawesome-webfont.eot
django_admin_json_editor/static/django_admin_json_editor/fontawesome/fonts/fontawesome-webfont.svg
django_admin_json_editor/static/django_admin_json_editor/fontawesome/fonts/fontawesome-webfont.ttf
django_admin_json_editor/static/django_admin_json_editor/fontawesome/fonts/fontawesome-webfont.woff
django_admin_json_editor/static/django_admin_json_editor/fontawesome/fonts/fontawesome-webfont.woff2
django_admin_json_editor/static/django_admin_json_editor/jquery/jquery.min.js
django_admin_json_editor/static/django_admin_json_editor/jsoneditor/jsoneditor.min.js
django_admin_json_editor/static/django_admin_json_editor/sceditor/jquery.sceditor.bbcode.min.js
django_admin_json_editor/static/django_admin_json_editor/sceditor/jquery.sceditor.default.min.css
